fb_gapi/__init__.py
fb_gapi/client.py
fb_gapi/exceptions.py
fb_gapi/utils.py
fb_gapi-0.1.28.dist-info/METADATA
fb_gapi-0.1.28.dist-info/WHEEL
fb_gapi-0.1.28.dist-info/top_level.txt
fb_gapi-0.1.28.dist-info/RECORD
