Metadata-Version: 2.4
Name: fb-gapi
Version: 0.1.28
Summary: A lightweight Python Sync / Async SDK for sending messages via Facebook Messenger
Author-email: Jayed <jayedbinjahangir@gmail.com>
License-Expression: MIT AND (Apache-2.0 OR BSD-2-Clause)
Project-URL: Homepage, https://github.com/jayeeed/fb-gapi
Requires-Python: >=3.9
Requires-Dist: requests
Requires-Dist: httpx
Requires-Dist: aiofiles
Requires-Dist: httpx-retries
